{
  "image_name": "testeDM",
  "source_file": "testeDM_www.naver.com.png",
  "source_sha256": "617b93c25cfe8e58a9ee97e0ab1851346db841db6502285cdecaedb78e79a023",
  "landing_url": "https://www.naver.com",
  "source_dimensions": {
    "width": 700,
    "height": 3335
  },
  "cta_button": {
    "file": "005_cta_button.png",
    "x": 237,
    "y": 1215,
    "width": 226,
    "height": 48
  },
  "slice_count": 11,
  "slices": [
    {
      "file": "001_hero.png",
      "x": 0,
      "y": 0,
      "width": 700,
      "height": 650
    },
    {
      "file": "002_intro.png",
      "x": 0,
      "y": 650,
      "width": 700,
      "height": 436
    },
    {
      "file": "003_before_cta.png",
      "x": 0,
      "y": 1086,
      "width": 700,
      "height": 129
    },
    {
      "file": "004_cta_left.png",
      "x": 0,
      "y": 1215,
      "width": 237,
      "height": 48
    },
    {
      "file": "005_cta_button.png",
      "x": 237,
      "y": 1215,
      "width": 226,
      "height": 48
    },
    {
      "file": "006_cta_right.png",
      "x": 463,
      "y": 1215,
      "width": 237,
      "height": 48
    },
    {
      "file": "007_event_details.png",
      "x": 0,
      "y": 1263,
      "width": 700,
      "height": 196
    },
    {
      "file": "008_agenda.png",
      "x": 0,
      "y": 1459,
      "width": 700,
      "height": 498
    },
    {
      "file": "009_speakers.png",
      "x": 0,
      "y": 1957,
      "width": 700,
      "height": 350
    },
    {
      "file": "010_benefit_coin.png",
      "x": 0,
      "y": 2307,
      "width": 700,
      "height": 459
    },
    {
      "file": "011_challenge.png",
      "x": 0,
      "y": 2766,
      "width": 700,
      "height": 569
    }
  ],
  "pixel_reconstruction": "exact_match",
  "phase": "images_created",
  "created_at": "2026-06-10T08:20:10.809951+00:00"
}
